{
  "id": "vorspiel-mix",
  "title": "Vorspiel Mix",
  "description": "Den perfekte blandingen for å kickstarte kvelden og få alle i godt humør.",
  "language": "no",
  "shuffle": true,
  "requiresPlayers": true,
  "emoji": "🍻",
  "color": "hsl(140 80% 60%)",
  "items": [
    { "type": "challenge", "text": "{player}, velg en drikkepartner for de neste 3 rundene. Hver gang en av dere drikker, drikker den andre også." },
    { "type": "prompt", "text": "Hva er det flaueste kallenavnet du noensinne har hatt?" },
    { "type": "pointing", "text": "Hvem her er mest sannsynlig til å foreslå nachspiel kl. 02?" },
    { "type": "challenge", "text": "{player}, du får 10 sekunder til å nevne 5 ting man kan finne i et kjøleskap. Hvis du feiler, drikk." },
    { "type": "prompt", "text": "Fortell om en gang du prøvde å imponere noen, men feilet totalt." }
  ]
}
